{
    "configurations": [
        {
            "name": "Win32",
            "includePath": [
                "${workspaceFolder}/**"
            ],
            "defines": [
                "_DEBUG",
                "UNICODE",
                "_UNICODE"
            ],
            "windowsSdkVersion": "10.0.19041.0",
            "compilerPath": "C:\\Users\\daywa\\esp\\.espressif\\tools\\xtensa-esp32-elf\\esp-2021r2-patch5-8.4.0\\xtensa-esp32-elf\\bin\\xtensa-esp32-elf-gcc.exe",
            "cStandard": "c17",
            "cppStandard": "c++17",
            "intelliSenseMode": "windows-msvc-x64",
            "configurationProvider": "ms-vscode.makefile-tools",
            "compileCommands": "${workspaceFolder}/build/compile_commands.json"
        }
    ],
    "version": 4
}
